setup.py
dfnt_dists/Binomialdistribution.py
dfnt_dists/Gaussiandistribution.py
dfnt_dists/Generaldistribution.py
dfnt_dists/__init__.py
dfnt_dists.egg-info/PKG-INFO
dfnt_dists.egg-info/SOURCES.txt
dfnt_dists.egg-info/dependency_links.txt
dfnt_dists.egg-info/not-zip-safe
dfnt_dists.egg-info/top_level.txt